gitrenametool/__init__.py
gitrenametool/cli.py
gitrenametool/Utils/__init__.py
gitrenametool/Utils/FileUtil.py
gitrenametool/Utils/ShellUtil.py
gitrenametool/Utils/SubUtil.py
gitrenametool-0.0.1.dist-info/entry_points.txt
gitrenametool-0.0.1.dist-info/WHEEL
gitrenametool-0.0.1.dist-info/METADATA
gitrenametool-0.0.1.dist-info/RECORD
