Metadata-Version: 2.1
Name: gitrenametool
Version: 0.0.1
Summary: rename git`s files dirs 
Author: ArthurWang
Author-email: yahui9119@gmail.com
Requires-Python: >=3.8,<4.0
Classifier: Programming Language :: Python :: 3
Classifier: Programming Language :: Python :: 3.8
Classifier: Programming Language :: Python :: 3.9
Requires-Dist: click (>=8.0.1,<9.0.0)
